README.md
setup.py
zlyq_python_sdk.egg-info/PKG-INFO
zlyq_python_sdk.egg-info/SOURCES.txt
zlyq_python_sdk.egg-info/dependency_links.txt
zlyq_python_sdk.egg-info/top_level.txt
zlyqauth/__init__.py
zlyqauth/appToken.py
zlyqauth/sign.py
zlyqmodel/__init__.py
zlyqmodel/article.py
zlyqmodel/history.py
zlyqmodel/image.py
zlyqmodel/media.py
zlyqmodel/user.py
zlyqmodel/video.py
zlyqsync/__init__.py
zlyqsync/client.py