Metadata-Version: 1.0
Name: zlyq-python-sdk
Version: 0.0.3
Summary: data synchronization tools for zlyq service
Home-page: https://github.com/zlzz-rec/zlyq-python-sdk
Author: Clifford
Author-email: 290416118@qq.com
License: MIT Licence
Keywords: pip,pathtool,timetool,magetool,mage
Platform: any
